[{"title":"2024高清性感美丽女生壁纸","href":"//img2.woyaogexing.com/2024/03/18/0386b845262d3d08!360x640.png","date":"0318","month":"03","day":"18"},{"title":"2024高清干净文艺衬衫王源壁纸","href":"//img2.woyaogexing.com/2024/03/18/7380c67f6e33ea91!360x640.jpg","date":"0318","month":"03","day":"18"},{"title":"2024高清慵懒温柔女生ins壁纸","href":"//img2.woyaogexing.com/2024/03/18/8bdc225e91489878!360x640.jpg","date":"0318","month":"03","day":"18"},{"title":"2024高清简约草莓蛋糕动漫壁纸","href":"//img2.woyaogexing.com/2024/03/18/ef7bad27d00e4513!360x640.png","date":"0318","month":"03","day":"18"},{"title":"2024高清可爱女生动漫壁纸","href":"//img2.woyaogexing.com/2024/03/18/bf1c8e98e97997fa!360x640.png","date":"0318","month":"03","day":"18"},{"title":"2024高清单纯甜美女生动漫壁纸","href":"//img2.woyaogexing.com/2024/03/18/d894b508b451b5e4!360x640.png","date":"0318","month":"03","day":"18"},{"title":"温柔的绽放  风景壁纸","href":"//img2.woyaogexing.com/2024/03/18/be7288ae3b890194!360x640.jpg","date":"0318","month":"03","day":"18"},{"title":"2024 可爱简约 风景壁纸","href":"//img2.woyaogexing.com/2024/03/18/bc82e7208c1dc1b3!360x640.jpg","date":"0318","month":"03","day":"18"},{"title":"2024 自由空旷 风景壁纸","href":"//img2.woyaogexing.com/2024/03/18/57b39525ea7fcd49!360x640.jpg","date":"0318","month":"03","day":"18"},{"title":"2024 清新温柔 风景壁纸","href":"//img2.woyaogexing.com/2024/03/18/5616b6369422bc77!360x640.jpg","date":"0318","month":"03","day":"18"},{"title":"2024 温柔个性 女生壁纸","href":"//img2.woyaogexing.com/2024/03/18/5c66220e310e4fc6!360x640.jpg","date":"0318","month":"03","day":"18"},{"title":"2024 自由开朗 王源壁纸","href":"//img2.woyaogexing.com/2024/03/18/58944716b225e6e9!360x640.jpg","date":"0318","month":"03","day":"18"},{"title":"2024 冷静睿智 千玺壁纸","href":"//img2.woyaogexing.com/2024/03/18/d3b538978650b08d!360x640.jpg","date":"0318","month":"03","day":"18"},{"title":"20224 简约可爱 动漫壁纸","href":"//img2.woyaogexing.com/2024/03/18/3f6613227f44a9fa!360x640.jpg","date":"0318","month":"03","day":"18"},{"title":"2024 龙年好运 动漫壁纸","href":"//img2.woyaogexing.com/2024/03/18/0d4a7df1265f629a!360x640.jpg","date":"0318","month":"03","day":"18"},{"title":"2024 活泼可爱 动漫壁纸","href":"//img2.woyaogexing.com/2024/03/18/c02fc3bd17da8b34!360x640.jpg","date":"0318","month":"03","day":"18"},{"title":"2024 清新温柔 风景壁纸","href":"//img2.woyaogexing.com/2024/03/17/735ad72cb3c26b35!360x640.jpg","date":"0317","month":"03","day":"17"},{"title":"2024 浪漫个性 风景壁纸","href":"//img2.woyaogexing.com/2024/03/17/bc1dfabbee0c5aca!360x640.jpg","date":"0317","month":"03","day":"17"},{"title":"2024 简单个性 风景壁纸","href":"//img2.woyaogexing.com/2024/03/17/d0114393047918b3!360x640.jpg","date":"0317","month":"03","day":"17"},{"title":"2024 治愈温柔 风景壁纸","href":"//img2.woyaogexing.com/2024/03/17/acd86a23584cfe8b!360x640.jpg","date":"0317","month":"03","day":"17"},{"title":"2024 唯美 简约 风景壁纸","href":"//img2.woyaogexing.com/2024/03/17/c68c7eadb7115fe4!360x640.jpg","date":"0317","month":"03","day":"17"},{"title":"2024 开朗帅气 男生壁纸","href":"//img2.woyaogexing.com/2024/03/17/12392a0185cc5a71!360x640.jpg","date":"0317","month":"03","day":"17"},{"title":"2024 温柔千玺 个性壁纸","href":"//img2.woyaogexing.com/2024/03/17/5ec2e8f29d13959f!360x640.jpg","date":"0317","month":"03","day":"17"},{"title":"2024 发财 动漫壁纸","href":"//img2.woyaogexing.com/2024/03/17/0b471c0c57d43400!360x640.jpg","date":"0317","month":"03","day":"17"},{"title":"2024 时来运转 动漫壁纸","href":"//img2.woyaogexing.com/2024/03/17/e73ffc03780fe388!360x640.jpg","date":"0317","month":"03","day":"17"},{"title":"2024 有钱有闲 温柔 动漫壁纸","href":"//img2.woyaogexing.com/2024/03/17/009ab458c6825cf1!360x640.jpg","date":"0317","month":"03","day":"17"},{"title":"2024高清安静唯美小屋风景壁纸","href":"//img2.woyaogexing.com/2024/03/17/53d5387c9e80940b!360x640.jpg","date":"0317","month":"03","day":"17"},{"title":"2024高清蓝天奔跑袋鼠风景壁纸","href":"//img2.woyaogexing.com/2024/03/17/543aa9c63e1921c1!360x640.jpg","date":"0317","month":"03","day":"17"},{"title":"2024高清夕阳下公路风景壁纸","href":"//img2.woyaogexing.com/2024/03/17/88947262510681ee!360x640.png","date":"0317","month":"03","day":"17"},{"title":"2024高清黑夜绚丽烟花风景壁纸","href":"//img2.woyaogexing.com/2024/03/17/dcc3c717e91c7722!360x640.jpg","date":"0317","month":"03","day":"17"},{"title":"2024高清氛围感个性女生壁纸","href":"//img2.woyaogexing.com/2024/03/17/a9be6e7e6ea18684!360x640.jpg","date":"0317","month":"03","day":"17"},{"title":"2024高清清纯ins鞠婧祎壁纸","href":"//img2.woyaogexing.com/2024/03/17/7ab41d3d50d89e5d!360x640.jpg","date":"0317","month":"03","day":"17"},{"title":"2024高清帅气个性TFBOYS壁纸","href":"//img2.woyaogexing.com/2024/03/17/45b5b011cbbc486f!360x640.jpg","date":"0317","month":"03","day":"17"},{"title":"2024高清海绵宝宝可爱派大星动漫壁纸","href":"//img2.woyaogexing.com/2024/03/17/de569a3c868fb412!360x640.jpg","date":"0317","month":"03","day":"17"},{"title":"2024高清古风鲜花美女动漫壁纸","href":"//img2.woyaogexing.com/2024/03/17/f44cc1afe91c71e9!360x640.jpg","date":"0317","month":"03","day":"17"},{"title":"2024高清蓝发可爱女生动漫壁纸","href":"//img2.woyaogexing.com/2024/03/17/d68f376d8af5dc5a!360x640.jpg","date":"0317","month":"03","day":"17"},{"title":"2024高清唯美雪山风景壁纸","href":"//img2.woyaogexing.com/2024/03/16/535de4beb571d05d!360x640.jpg","date":"0316","month":"03","day":"16"},{"title":"2024高清清澈蔚蓝海面风景壁纸","href":"//img2.woyaogexing.com/2024/03/16/3e18b2ba80f4b016!360x640.jpg","date":"0316","month":"03","day":"16"},{"title":"2024高清摩登现代大都市风景壁纸","href":"//img2.woyaogexing.com/2024/03/16/64c195493d399df8!360x640.png","date":"0316","month":"03","day":"16"},{"title":"2024高清美味蛋挞炸鸡风景壁纸","href":"//img2.woyaogexing.com/2024/03/16/6158b4fc6bc52567!360x640.jpg","date":"0316","month":"03","day":"16"},{"title":"2024高清复古欧美女生壁纸","href":"//img2.woyaogexing.com/2024/03/16/89943ae47655515a!360x640.jpg","date":"0316","month":"03","day":"16"},{"title":"2024高清小清新文艺感男生壁纸","href":"//img2.woyaogexing.com/2024/03/16/2ae84878e4d9e9c9!360x640.jpg","date":"0316","month":"03","day":"16"},{"title":"2024高清英俊潇洒李敏镐男生壁纸","href":"//img2.woyaogexing.com/2024/03/16/064f3a7296970c6e!360x640.jpg","date":"0316","month":"03","day":"16"},{"title":"2024高清清纯校园风女生动漫壁纸","href":"//img2.woyaogexing.com/2024/03/16/9581ad5a01224b60!360x640.jpg","date":"0316","month":"03","day":"16"},{"title":"2024高清精美火烈鸟动漫壁纸","href":"//img2.woyaogexing.com/2024/03/16/a367960ea42c2854!360x640.jpg","date":"0316","month":"03","day":"16"},{"title":"2024高清帅气怪盗基德动漫壁纸","href":"//img2.woyaogexing.com/2024/03/16/ddacac3097a46adb!360x640.jpg","date":"0316","month":"03","day":"16"},{"title":"2024 温柔治愈 风景壁纸","href":"//img2.woyaogexing.com/2024/03/16/2d9fc557934e1d0f!360x640.jpg","date":"0316","month":"03","day":"16"},{"title":"2024 清幽典雅 风景壁纸","href":"//img2.woyaogexing.com/2024/03/16/ad767e0bc6b3dc5b!360x640.jpg","date":"0316","month":"03","day":"16"},{"title":"2024 温柔浪漫 风景壁纸","href":"//img2.woyaogexing.com/2024/03/16/5fdd397e9a17d3d8!360x640.jpg","date":"0316","month":"03","day":"16"},{"title":"2024 追寻自由 个性 女生壁纸","href":"//img2.woyaogexing.com/2024/03/16/aae22ba26ab3b082!360x640.jpg","date":"0316","month":"03","day":"16"},{"title":"2024 享受阳光 女生壁纸","href":"//img2.woyaogexing.com/2024/03/16/81f967d9879a6d19!360x640.jpg","date":"0316","month":"03","day":"16"},{"title":"2024 多才多艺 王源开朗壁纸","href":"//img2.woyaogexing.com/2024/03/16/6c1c899cc5a43397!360x640.jpg","date":"0316","month":"03","day":"16"},{"title":"2024 王俊凯英俊 壁纸","href":"//img2.woyaogexing.com/2024/03/16/3a9efb3d21bd3342!360x640.jpg","date":"0316","month":"03","day":"16"},{"title":"2024 浪漫且最美的相遇 动漫壁纸","href":"//img2.woyaogexing.com/2024/03/16/982687645c7ba281!360x640.jpg","date":"0316","month":"03","day":"16"},{"title":"2024 温柔年味 动漫壁纸","href":"//img2.woyaogexing.com/2024/03/16/bee9c0b83ccf6d77!360x640.jpg","date":"0316","month":"03","day":"16"},{"title":"2024 顺顺利利 动漫壁纸","href":"//img2.woyaogexing.com/2024/03/16/100bbbdc44ad43ba!360x640.jpg","date":"0316","month":"03","day":"16"},{"title":"2024 简约个性 风景壁纸","href":"//img2.woyaogexing.com/2024/03/15/cdd87f672ee03a03!360x640.jpg","date":"0315","month":"03","day":"15"},{"title":"2024 浪漫温柔 风景壁纸","href":"//img2.woyaogexing.com/2024/03/15/f6334438b1b22b5f!360x640.jpg","date":"0315","month":"03","day":"15"},{"title":"2024 温柔清新 风景壁纸","href":"//img2.woyaogexing.com/2024/03/15/4fbdab88af427ca0!360x640.jpg","date":"0315","month":"03","day":"15"},{"title":"2024 温柔活力 女生壁纸","href":"//img2.woyaogexing.com/2024/03/15/1158fc84c46dea89!360x640.jpg","date":"0315","month":"03","day":"15"},{"title":"2024 简单个性 王源壁纸","href":"//img2.woyaogexing.com/2024/03/15/0b6e31821566deb7!360x640.jpg","date":"0315","month":"03","day":"15"},{"title":"2024 温柔帅气 千玺壁纸","href":"//img2.woyaogexing.com/2024/03/15/e0b559955d246e52!360x640.jpg","date":"0315","month":"03","day":"15"},{"title":"2024 简约可爱 动漫壁纸","href":"//img2.woyaogexing.com/2024/03/15/b876a23c78f25c3d!360x640.jpg","date":"0315","month":"03","day":"15"},{"title":"2024 可爱简单 动漫壁纸","href":"//img2.woyaogexing.com/2024/03/15/6d96cb3dfa8a5ea4!360x640.jpg","date":"0315","month":"03","day":"15"},{"title":"2024 幸运顺利 动漫壁纸","href":"//img2.woyaogexing.com/2024/03/15/a8a876d1f54def48!360x640.jpg","date":"0315","month":"03","day":"15"},{"title":"2024 简单个性 动漫壁纸","href":"//img2.woyaogexing.com/2024/03/15/79a90656b9175d6e!360x640.jpg","date":"0315","month":"03","day":"15"},{"title":"2024高清小清新绿树天空风景壁纸","href":"//img2.woyaogexing.com/2024/03/15/e4de410bed0a24f3!360x640.png","date":"0315","month":"03","day":"15"},{"title":"2024高清绿色海水风景壁纸","href":"//img2.woyaogexing.com/2024/03/15/3c8c4517d0ecd384!360x640.jpg","date":"0315","month":"03","day":"15"},{"title":"2024高清清凉美味冰淇淋风景壁纸","href":"//img2.woyaogexing.com/2024/03/15/88c868e815fec6e3!360x640.jpg","date":"0315","month":"03","day":"15"},{"title":"2024高清小清新樱花盛开风景壁纸","href":"//img2.woyaogexing.com/2024/03/15/f621aa4ed90b0a3a!360x640.jpg","date":"0315","month":"03","day":"15"},{"title":"2024高清小清新ins女生壁纸","href":"//img2.woyaogexing.com/2024/03/15/bf0b9ee9cde05756!360x640.jpg","date":"0315","month":"03","day":"15"},{"title":"2024高清帅气易烊千玺壁纸","href":"//img2.woyaogexing.com/2024/03/15/ab2308d7db880337!360x640.jpg","date":"0315","month":"03","day":"15"},{"title":"2024高清氛围感唯美女生壁纸","href":"//img2.woyaogexing.com/2024/03/15/c2ed0f8df5ab76ce!360x640.jpg","date":"0315","month":"03","day":"15"},{"title":"2024高清火影忍者动漫壁纸","href":"//img2.woyaogexing.com/2024/03/15/61d09d8bfcf93126!360x640.jpg","date":"0315","month":"03","day":"15"},{"title":"2024高清氛围感男生动漫壁纸","href":"//img2.woyaogexing.com/2024/03/15/61ab249483a3e372!360x640.jpg","date":"0315","month":"03","day":"15"},{"title":"2024高清黑白线条简约男生动漫壁纸","href":"//img2.woyaogexing.com/2024/03/15/fe45279ec4d1a088!360x640.jpg","date":"0315","month":"03","day":"15"},{"title":"2024高清可爱阿童木动漫壁纸","href":"//img2.woyaogexing.com/2024/03/14/14acbee96c340125!360x640.png","date":"0314","month":"03","day":"14"},{"title":"2024高清山水清新风景壁纸","href":"//img2.woyaogexing.com/2024/03/14/f6bc8319bf503bc6!360x640.jpg","date":"0314","month":"03","day":"14"},{"title":"2024高清花朵唯美风景壁纸","href":"//img2.woyaogexing.com/2024/03/14/f97d61b78b393327!360x640.png","date":"0314","month":"03","day":"14"},{"title":"2024高清雪山唯美风景壁纸","href":"//img2.woyaogexing.com/2024/03/14/82c29b52c162c281!360x640.jpg","date":"0314","month":"03","day":"14"},{"title":"2024高清美味面包风景壁纸","href":"//img2.woyaogexing.com/2024/03/14/ae73f3afda36cdd7!360x640.jpg","date":"0314","month":"03","day":"14"},{"title":"2024高清个性活泼男生壁纸","href":"//img2.woyaogexing.com/2024/03/14/d3fdf32b82a8530f!360x640.jpg","date":"0314","month":"03","day":"14"},{"title":"2024高清甜美清纯超性感女生壁纸","href":"//img2.woyaogexing.com/2024/03/14/ff092b4411bf7ab9!360x640.jpg","date":"0314","month":"03","day":"14"},{"title":"2024高清帅气男孩壁纸","href":"//img2.woyaogexing.com/2024/03/14/1ab5666ccda9744d!360x640.jpg","date":"0314","month":"03","day":"14"},{"title":"2024高清可爱甜美女生动漫壁纸","href":"//img2.woyaogexing.com/2024/03/14/1cfaabd72e72be2c!360x640.jpg","date":"0314","month":"03","day":"14"},{"title":"2024高清带字处女座动漫壁纸","href":"//img2.woyaogexing.com/2024/03/14/f276004fc3a7b227!360x640.jpg","date":"0314","month":"03","day":"14"},{"title":"2024 浪漫的水墨 风景壁纸","href":"//img2.woyaogexing.com/2024/03/14/6a63debc00760791!360x640.jpg","date":"0314","month":"03","day":"14"},{"title":"2024 甜蜜的治愈 风景壁纸","href":"//img2.woyaogexing.com/2024/03/14/21265b61b08a8e96!360x640.jpg","date":"0314","month":"03","day":"14"},{"title":"2024 温暖个性 风景壁纸","href":"//img2.woyaogexing.com/2024/03/14/eb0ab4d652b61686!360x640.jpg","date":"0314","month":"03","day":"14"},{"title":"2024 治愈浪漫 风景壁纸","href":"//img2.woyaogexing.com/2024/03/14/c416a5e7c73ac058!360x640.jpg","date":"0314","month":"03","day":"14"},{"title":"2024 温柔芬芳 风景壁纸","href":"//img2.woyaogexing.com/2024/03/14/f85b1cb1ece5efb4!360x640.jpg","date":"0314","month":"03","day":"14"},{"title":"2024 感性优雅 女生壁纸","href":"//img2.woyaogexing.com/2024/03/14/9282531304b15154!360x640.jpg","date":"0314","month":"03","day":"14"},{"title":"2024 温柔可爱淑女 个性壁纸","href":"//img2.woyaogexing.com/2024/03/14/a84a1fa57bddc61c!360x640.jpg","date":"0314","month":"03","day":"14"},{"title":"2024 温柔帅气 千玺 壁纸","href":"//img2.woyaogexing.com/2024/03/14/1dac634445bc428e!360x640.jpg","date":"0314","month":"03","day":"14"},{"title":"2024 温柔萌系 女生 动漫壁纸","href":"//img2.woyaogexing.com/2024/03/14/d22bfa21a9a2d5f0!360x640.jpg","date":"0314","month":"03","day":"14"},{"title":"2024 平安喜乐 动漫壁纸","href":"//img2.woyaogexing.com/2024/03/14/e475ed23c1eead81!360x640.jpg","date":"0314","month":"03","day":"14"},{"title":"2024高清静谧小村庄风景壁纸","href":"//img2.woyaogexing.com/2024/03/13/93603db98cd10d81!360x640.jpg","date":"0313","month":"03","day":"13"},{"title":"2024高清平静浪花风景壁纸","href":"//img2.woyaogexing.com/2024/03/13/8047a993ded948eb!360x640.jpg","date":"0313","month":"03","day":"13"},{"title":"2024高清险峻高山风景壁纸","href":"//img2.woyaogexing.com/2024/03/13/c0244663cc9cb760!360x640.jpg","date":"0313","month":"03","day":"13"},{"title":"2024高清可口美食花卷风景壁纸","href":"//img2.woyaogexing.com/2024/03/13/28aacf3a417384d8!360x640.jpg","date":"0313","month":"03","day":"13"},{"title":"2024高清超性感不露脸女生壁纸","href":"//img2.woyaogexing.com/2024/03/13/791fe7aafc3460d1!360x640.jpg","date":"0313","month":"03","day":"13"},{"title":"2024高清高级感王俊凯壁纸","href":"//img2.woyaogexing.com/2024/03/13/39ba200fc489d7ca!360x640.jpg","date":"0313","month":"03","day":"13"},{"title":"2024高清帅气才华横溢男生壁纸","href":"//img2.woyaogexing.com/2024/03/13/275a06e72e47065f!360x640.jpg","date":"0313","month":"03","day":"13"},{"title":"2024高清纯洁闺蜜情动漫壁纸","href":"//img2.woyaogexing.com/2024/03/13/9ca3df67ff4bba89!360x640.jpg","date":"0313","month":"03","day":"13"},{"title":"2024高清慵懒成熟女生动漫壁纸","href":"//img2.woyaogexing.com/2024/03/13/19b195f3794a62e1!360x640.jpg","date":"0313","month":"03","day":"13"},{"title":"2024高清学生校服男生动漫壁纸","href":"//img2.woyaogexing.com/2024/03/13/f7002cf5479b4243!360x640.jpg","date":"0313","month":"03","day":"13"},{"title":"2024 尘埃落地 个性壁纸","href":"//img2.woyaogexing.com/2024/03/13/7c1a86711f6ec8f6!360x640.jpg","date":"0313","month":"03","day":"13"},{"title":"2024 清新治愈 风景壁纸","href":"//img2.woyaogexing.com/2024/03/13/a8b1bb25a2c8aab2!360x640.jpg","date":"0313","month":"03","day":"13"},{"title":"2024 温柔浪漫 风景壁纸","href":"//img2.woyaogexing.com/2024/03/13/fd1eba288c25ea0f!360x640.jpg","date":"0313","month":"03","day":"13"},{"title":"2024 优雅帅气 女生壁纸","href":"//img2.woyaogexing.com/2024/03/13/bdf5d20c6068d1ba!360x640.jpg","date":"0313","month":"03","day":"13"},{"title":"2024 自由舒适 女生壁纸","href":"//img2.woyaogexing.com/2024/03/13/f7d7049d3c617ec8!360x640.jpg","date":"0313","month":"03","day":"13"},{"title":"2024 清新干净 帅哥壁纸","href":"//img2.woyaogexing.com/2024/03/13/bcde7f7f950351d9!360x640.jpg","date":"0313","month":"03","day":"13"},{"title":"2024 个性神龙 动漫壁纸","href":"//img2.woyaogexing.com/2024/03/13/b53f5771a89583b7!360x640.jpg","date":"0313","month":"03","day":"13"},{"title":"2024 简约霸气 动漫壁纸","href":"//img2.woyaogexing.com/2024/03/13/d1820ced0995f71f!360x640.jpg","date":"0313","month":"03","day":"13"},{"title":"2024 美好祝愿  动漫壁纸","href":"//img2.woyaogexing.com/2024/03/13/77eadbc9eedb9ca3!360x640.jpg","date":"0313","month":"03","day":"13"},{"title":"2024 冷酷帅气 男生 动漫壁纸","href":"//img2.woyaogexing.com/2024/03/13/4859424e41ffd100!360x640.jpg","date":"0313","month":"03","day":"13"},{"title":"2024高清海水清澈风景壁纸","href":"//img2.woyaogexing.com/2024/03/12/ed79265a36d006b0!360x640.jpg","date":"0312","month":"03","day":"12"},{"title":"2024高清鲜艳郁金香风景壁纸","href":"//img2.woyaogexing.com/2024/03/12/3c4186493267a8b0!360x640.jpg","date":"0312","month":"03","day":"12"},{"title":"2024高清唯美公路夜景风景壁纸","href":"//img2.woyaogexing.com/2024/03/12/a372ad680ca238d4!360x640.png","date":"0312","month":"03","day":"12"},{"title":"2024高清缤纷多彩冰淇淋风景壁纸","href":"//img2.woyaogexing.com/2024/03/12/5d0b82f2d21dc1a3!360x640.png","date":"0312","month":"03","day":"12"},{"title":"2024高清小清新个性男生壁纸","href":"//img2.woyaogexing.com/2024/03/12/b51a4d376dcdebb4!360x640.jpg","date":"0312","month":"03","day":"12"},{"title":"2024高清高颜值帅气李敏镐壁纸","href":"//img2.woyaogexing.com/2024/03/12/c6c9a80ce0eb656f!360x640.jpg","date":"0312","month":"03","day":"12"},{"title":"2024高清复古唯美欧美女生壁纸","href":"//img2.woyaogexing.com/2024/03/12/2cb33d75a089ee55!360x640.jpg","date":"0312","month":"03","day":"12"},{"title":"2024高清黑白热血佐助火影忍者动漫壁纸","href":"//img2.woyaogexing.com/2024/03/12/fd120615a14d969c!360x640.jpg","date":"0312","month":"03","day":"12"},{"title":"2024高清神秘炫酷动漫壁纸","href":"//img2.woyaogexing.com/2024/03/12/5d0d7a3cd20189fa!360x640.jpg","date":"0312","month":"03","day":"12"},{"title":"2024高清灵动可爱猫头鹰动漫壁纸","href":"//img2.woyaogexing.com/2024/03/12/595991d24e15b34c!360x640.jpg","date":"0312","month":"03","day":"12"},{"title":"2024 清新温柔 风景壁纸","href":"//img2.woyaogexing.com/2024/03/12/505594d7a780a0cf!360x640.jpg","date":"0312","month":"03","day":"12"},{"title":"2024 书的海洋  风景壁纸","href":"//img2.woyaogexing.com/2024/03/12/3441e8676635263c!360x640.jpg","date":"0312","month":"03","day":"12"},{"title":"2024 温柔安静  风景壁纸","href":"//img2.woyaogexing.com/2024/03/12/95fe512c5934d3ac!360x640.jpg","date":"0312","month":"03","day":"12"},{"title":"2024 自由浪漫 个性壁纸","href":"//img2.woyaogexing.com/2024/03/12/ad3fc99e3ab98d84!360x640.jpg","date":"0312","month":"03","day":"12"},{"title":"2024 温柔的奔向阳光 女生壁纸","href":"//img2.woyaogexing.com/2024/03/12/acf2f2e4a70c66ec!360x640.jpg","date":"0312","month":"03","day":"12"},{"title":"2024 优雅小生 帅气王俊凯  壁纸","href":"//img2.woyaogexing.com/2024/03/12/f79b9bc6e4d1c855!360x640.jpg","date":"0312","month":"03","day":"12"},{"title":"2024 优雅可爱 女生壁纸","href":"//img2.woyaogexing.com/2024/03/12/757489a57ea01654!360x640.jpg","date":"0312","month":"03","day":"12"},{"title":"2024 幸福安心 动漫壁纸","href":"//img2.woyaogexing.com/2024/03/12/51158ec7de3e75e6!360x640.jpg","date":"0312","month":"03","day":"12"},{"title":"2024 平安喜乐个性 动漫壁纸","href":"//img2.woyaogexing.com/2024/03/12/38906366996b36ce!360x640.jpg","date":"0312","month":"03","day":"12"},{"title":"2024 温柔的小牛 动漫壁纸","href":"//img2.woyaogexing.com/2024/03/12/5d844167d69165e6!360x640.jpg","date":"0312","month":"03","day":"12"},{"title":"2024高清海边大都市风景壁纸","href":"//img2.woyaogexing.com/2024/03/11/27687c2aca903d19!360x640.png","date":"0311","month":"03","day":"11"},{"title":"2024高清鲜花唯美风景壁纸","href":"//img2.woyaogexing.com/2024/03/11/dd0d5242ef4ec257!360x640.png","date":"0311","month":"03","day":"11"},{"title":"2024高清波涛海浪风景壁纸","href":"//img2.woyaogexing.com/2024/03/11/d2dd7f20fef42678!360x640.png","date":"0311","month":"03","day":"11"},{"title":"2024高清树木圆月风景壁纸","href":"//img2.woyaogexing.com/2024/03/11/fd59d2cc0261544a!360x640.png","date":"0311","month":"03","day":"11"},{"title":"2024高清帅气TFBOYS壁纸","href":"//img2.woyaogexing.com/2024/03/11/69695655b905ce51!360x640.jpg","date":"0311","month":"03","day":"11"},{"title":"2024高清ins小清新女生壁纸","href":"//img2.woyaogexing.com/2024/03/11/7ac35282fa1c8ab5!360x640.jpg","date":"0311","month":"03","day":"11"},{"title":"2024高清年少帅气男生壁纸","href":"//img2.woyaogexing.com/2024/03/11/24da0e3d3d9fa383!360x640.jpg","date":"0311","month":"03","day":"11"},{"title":"2024高清氛围感帅气男生动漫壁纸","href":"//img2.woyaogexing.com/2024/03/11/2e126e3c57894bc6!360x640.jpg","date":"0311","month":"03","day":"11"},{"title":"2024高清可爱粉色头发女生动漫壁纸","href":"//img2.woyaogexing.com/2024/03/11/b592e36be3d43cb2!360x640.jpg","date":"0311","month":"03","day":"11"},{"title":"2024高清春暖花开唯美动漫壁纸","href":"//img2.woyaogexing.com/2024/03/11/48b5b3c7dd9fcd41!360x640.png","date":"0311","month":"03","day":"11"},{"title":"2024 时间的迷雾 风景壁纸","href":"//img2.woyaogexing.com/2024/03/11/1684057901108e1c!360x640.jpg","date":"0311","month":"03","day":"11"},{"title":"2024 安宁释然 风景壁纸","href":"//img2.woyaogexing.com/2024/03/11/a8e7f25980c4ba50!360x640.jpg","date":"0311","month":"03","day":"11"},{"title":"2024 浪漫的花季 风景壁纸","href":"//img2.woyaogexing.com/2024/03/11/996a38314eb3914c!360x640.jpg","date":"0311","month":"03","day":"11"},{"title":"2024 冰香柠檬  个性风景壁纸","href":"//img2.woyaogexing.com/2024/03/11/70ff79f7a581ab93!360x640.jpg","date":"0311","month":"03","day":"11"},{"title":"2024 温柔艺术 可爱 女生壁纸","href":"//img2.woyaogexing.com/2024/03/11/1cbc29fe45bf8102!360x640.jpg","date":"0311","month":"03","day":"11"},{"title":"2024 精致优雅 女生壁纸","href":"//img2.woyaogexing.com/2024/03/11/39fb83f92831b256!360x640.jpg","date":"0311","month":"03","day":"11"},{"title":"2024 个性青年 千玺 壁纸","href":"//img2.woyaogexing.com/2024/03/11/b7c397a4bff18cb3!360x640.jpg","date":"0311","month":"03","day":"11"},{"title":"2024 温柔好运 动漫壁纸","href":"//img2.woyaogexing.com/2024/03/11/e495be092ebe2888!360x640.jpg","date":"0311","month":"03","day":"11"},{"title":"2024 温柔简约 花纹  动漫壁在","href":"//img2.woyaogexing.com/2024/03/11/68001a636c74bb72!360x640.jpg","date":"0311","month":"03","day":"11"},{"title":"2024 活泼可爱 女生动漫壁纸","href":"//img2.woyaogexing.com/2024/03/11/097b69632f6cf9bf!360x640.jpg","date":"0311","month":"03","day":"11"}]