[{"code":"472d2d553939704f4fa77979","likes":"13066","date":"1 year"},{"code":"698474889e81bac7a7e5e4cc","likes":"13036","date":"4 years"},{"code":"fff2d8ead7bbbca37f113946","likes":"13029","date":"8 months"},{"code":"ecf9fffffbebffe7ccf8cba6","likes":"13008","date":"1 year"},{"code":"9a3b3bc08261e2c799f2ecbe","likes":"12994","date":"9 months"},{"code":"402218865439c68b59d7b19d","likes":"12990","date":"3 years"},{"code":"caf7e3edffecf6dfebe4bad4","likes":"12959","date":"3 years"},{"code":"f7ecdee9dac19ed2c654bab9","likes":"12952","date":"1 year"},{"code":"f5e8c7ecccb2deb6abac7088","likes":"12935","date":"1 year"},{"code":"ffd5e5ffffdda0ffe681f5ff","likes":"12872","date":"4 years"},{"code":"ff8787f8c4b4e5ebb2bce29e","likes":"12870","date":"1 year"},{"code":"ece3ce7390724f6f523a4d39","likes":"12858","date":"7 months"},{"code":"5f6f52a9b388fefae0b99470","likes":"12834","date":"7 months"},{"code":"155263ff6f3cff9a3cffc93c","likes":"12820","date":"6 years"},{"code":"fcf8ecd0e8f279a3b1456268","likes":"12751","date":"3 years"},{"code":"61764b9ba17bcfb997fad6a5","likes":"12722","date":"1 year"},{"code":"7c9473cfdac8e8eae6cdd0cb","likes":"12717","date":"3 years"},{"code":"e1f2fbf1f9f9f3dfe3e9b2bc","likes":"12694","date":"4 years"},{"code":"1a374d4068826998abb1d0e0","likes":"12671","date":"2 years"},{"code":"e0ece4f7f2e7d8d3cd797a7e","likes":"12616","date":"3 years"},{"code":"b2a4ffffb4b4ffdeb4fdf7c3","likes":"12542","date":"1 year"},{"code":"f5eee6fff8e3f3d7cae6a4b4","likes":"12523","date":"5 months"},{"code":"ffd4b2fff6bdceedc786c8bc","likes":"12496","date":"1 year"},{"code":"94b49fcee5d0fcf8e8ecb390","likes":"12493","date":"1 year"},{"code":"f0e5cff7f6f2c8c6c64b6587","likes":"12490","date":"2 years"},{"code":"ccf6c8fafcc2f6d6adf9c0c0","likes":"12455","date":"3 years"},{"code":"2a2f4f917fb3e5beecfde2f3","likes":"12451","date":"1 year"},{"code":"e97777ff9f9ffcddb0fffad7","likes":"12440","date":"1 year"},{"code":"f8f0e5eadbc8dac0a3102c57","likes":"12381","date":"10 months"},{"code":"0b244719376d576cbca5d7e8","likes":"12380","date":"1 year"},{"code":"ffe6e6ffabe1a685e26155a6","likes":"12330","date":"3 years"},{"code":"2f5d625e8b7ea7c4bcdfeeea","likes":"12312","date":"3 years"},{"code":"645cbba084dcbface2ebc7e6","likes":"12306","date":"1 year"},{"code":"edcfa9e89f71d57149aa4a30","likes":"12305","date":"3 years"},{"code":"dbd0c0faeee0f9e4c8f9cf93","likes":"12299","date":"2 years"},{"code":"635985443c6839305318122b","likes":"12253","date":"1 year"},{"code":"f5efe7d8c4b64f709c213555","likes":"12235","date":"1 year"},{"code":"d9d7f1fffddee7fbbeffcbcb","likes":"12190","date":"2 years"},{"code":"6fe7dd3490de6639a6521262","likes":"12175","date":"8 years"},{"code":"3038413a4750d72323eeeeee","likes":"12106","date":"7 years"}]