[{"code":"362706464e2eacb992e9e5d6","likes":"10669","date":"2 years"},{"code":"f0e4d7f5c0c0ff71719fd8df","likes":"10637","date":"3 years"},{"code":"181d31678983e6ddc4f0e9d2","likes":"10634","date":"1 year"},{"code":"fff9caffdeb4ffb4b4b2a4ff","likes":"10616","date":"1 year"},{"code":"94a684aec3aee4e4d0ffeef4","likes":"10605","date":"9 months"},{"code":"f7f7e8c7cfb79dad7f557174","likes":"10595","date":"3 years"},{"code":"bbd6b8aec2b694af9fdbe4c6","likes":"10582","date":"1 year"},{"code":"e6e6e6c5a880532e1c0f0f0f","likes":"10570","date":"3 years"},{"code":"232931393e464ecca3eeeeee","likes":"10534","date":"6 years"},{"code":"0f044c141e61787a91eeeeee","likes":"10523","date":"2 years"},{"code":"440a6793329eb4aee8ffe3fe","likes":"10502","date":"3 years"},{"code":"f7a4a4febe8cfffbc1b6e2a1","likes":"10496","date":"1 year"},{"code":"cee5d0f3f0d7d8b3845e454b","likes":"10484","date":"3 years"},{"code":"f1ecc3c9d8b657837b515e63","likes":"10387","date":"2 years"},{"code":"ffb3b3ffdba4ffe9aec1efff","likes":"10381","date":"1 year"},{"code":"ffc5c5ffebd8c7dca789b9ad","likes":"10377","date":"6 months"},{"code":"f3d5c0d4b499889eaf506d84","likes":"10373","date":"2 years"},{"code":"194350ff8882ffc2b49dbeb9","likes":"10338","date":"3 years"},{"code":"caf7e3f8ededf6dfebe4bad4","likes":"10328","date":"3 years"},{"code":"f6d7a7f6eabec8e3d487aaaa","likes":"10313","date":"2 years"},{"code":"f1d4d4ddb6c6ac8daf484c7f","likes":"10300","date":"4 years"},{"code":"002b5b2b4865256d858fe3cf","likes":"10274","date":"1 year"},{"code":"faf3f3e1e5eaa7bbc7da7f8f","likes":"10233","date":"3 years"},{"code":"3932324d45458d6262ed8d8d","likes":"10224","date":"6 years"},{"code":"6e85b7b2c8dfc4d7e0f8f9d7","likes":"10205","date":"1 year"},{"code":"ffc6acfff6dcc4c1a49e9fa5","likes":"10187","date":"10 months"},{"code":"99bbadebd8b7c6a9a39a8194","likes":"10181","date":"3 years"},{"code":"2040513b697884a9accae8d5","likes":"10170","date":"4 years"},{"code":"e8e8e85588a314537400334e","likes":"10162","date":"5 years"},{"code":"1c0a00361500603601cc9544","likes":"10151","date":"2 years"},{"code":"00e0ff74f9ffa6fff2e8ffe8","likes":"10147","date":"7 years"},{"code":"3aa6b9ffd0d0ff9eaac1ece4","likes":"10143","date":"11 months"},{"code":"d2e0fbf9f3ccd7e5ca8eaccd","likes":"10130","date":"8 months"},{"code":"252525ff0000af0404414141","likes":"10114","date":"4 years"},{"code":"f9f3dffdfce5d7e9f7f4d19b","likes":"10113","date":"2 years"},{"code":"f1f3f8d6e0f08d93ab393b44","likes":"10104","date":"3 years"},{"code":"f6ffdee3f2c1c9dbb2aac8a7","likes":"10091","date":"1 year"},{"code":"fba1b7ffd1dafff0f5ffdbaa","likes":"10091","date":"10 months"},{"code":"495c837a86b6a8a4cec8b6e2","likes":"10061","date":"1 year"},{"code":"151515301b3f3c415cb4a5a5","likes":"10056","date":"3 years"}]