[{"code":"3c486bf0f0f0f9d949f45050","likes":"6141","date":"6 months"},{"code":"b9eddd87cbb9569daa577d86","likes":"7458","date":"6 months"},{"code":"f2e3db41644a263a29e86a33","likes":"6411","date":"6 months"},{"code":"d14d72ffababfcc8d1fef2f4","likes":"11082","date":"6 months"},{"code":"070a52d21312ed2b2af15a59","likes":"3517","date":"6 months"},{"code":"3936464f45576d5d6ef4eee0","likes":"6985","date":"6 months"},{"code":"fff3e2ffe5cafa9884e74646","likes":"9295","date":"6 months"},{"code":"f9e2af009fbd21006277037b","likes":"2780","date":"6 months"},{"code":"fdf4f5e8a0bfba90c6c0dbea","likes":"10407","date":"6 months"},{"code":"454545ff6000ffa559ffe6c7","likes":"7612","date":"6 months"},{"code":"ddffbbc7e9b0b3c99ca4bc92","likes":"9514","date":"6 months"},{"code":"f6f1e9ffd93dff84004f200d","likes":"5848","date":"6 months"},{"code":"89375fce5959bacddbf3e8ff","likes":"2115","date":"6 months"},{"code":"f5f3c127e1c10ea2932f0f5d","likes":"2337","date":"6 months"},{"code":"0b244719376d576cbca5d7e8","likes":"9842","date":"7 months"},{"code":"feff86b0daffb9e9fcdaf5ff","likes":"4976","date":"7 months"},{"code":"b2a4ffffb4b4ffdeb4fdf7c3","likes":"10246","date":"7 months"},{"code":"a9907ef3debaabc4aa675d50","likes":"13612","date":"7 months"},{"code":"57c5b61598951a5f7a002b5b","likes":"6941","date":"7 months"},{"code":"000000262a56b8621be3ccae","likes":"3907","date":"7 months"},{"code":"7aa874f7db6aebb02dd864a9","likes":"2407","date":"7 months"},{"code":"9a208ce11299ffeaeaf5c6ec","likes":"4185","date":"7 months"},{"code":"7149c6fc2947fe6244ffdeb9","likes":"3151","date":"7 months"},{"code":"fff2ccffd966f4b183dfa67b","likes":"7654","date":"7 months"},{"code":"245953408e91e49393d8d8d8","likes":"5248","date":"7 months"},{"code":"867070d5b4b4e4d0d0f5ebeb","likes":"15784","date":"7 months"},{"code":"fff4e0ffbf9bb460604d4d4d","likes":"7180","date":"7 months"},{"code":"f9f5ebe4dccfea5455002b5b","likes":"6322","date":"7 months"},{"code":"f6f1f119a7ce146c94000000","likes":"6565","date":"7 months"},{"code":"bbd6b8aec2b694af9fdbe4c6","likes":"9459","date":"7 months"},{"code":"2d27274135438f43eef0eb8d","likes":"2808","date":"7 months"},{"code":"00235be21818ffdd8398dfd6","likes":"3964","date":"7 months"},{"code":"ccd5aee9edc9fefae0faedcd","likes":"14227","date":"7 months"},{"code":"aa77ffc9eeff97deff62cdff","likes":"5064","date":"7 months"},{"code":"37306b66347f9e4784d27685","likes":"8543","date":"7 months"},{"code":"8d7b68a4907cc8b6a6f1dec9","likes":"18982","date":"7 months"},{"code":"ffacacffbfa9ffebb4fbffb1","likes":"11637","date":"7 months"},{"code":"ede9d5e7ab9adf7857617143","likes":"5044","date":"7 months"},{"code":"2c33332e4f4f0e8388cbe4de","likes":"9934","date":"7 months"},{"code":"5391653f497ff7c04af8f5e4","likes":"3241","date":"7 months"}]