[{"code":"222831393e4600adb5eeeeee","likes":"65207","date":"8 years"},{"code":"e3fdfdcbf1f5a6e3e971c9ce","likes":"36015","date":"7 years"},{"code":"f9f7f7dbe2ef3f72af112d4e","likes":"32534","date":"7 years"},{"code":"ffc7c7ffe2e2f6f6f68785a2","likes":"32191","date":"6 years"},{"code":"fff5e4ffe3e1ffd1d1ff9494","likes":"30844","date":"1 year"},{"code":"ad8b73ceab93e3caa5fffbe9","likes":"30235","date":"2 years"},{"code":"08d9d6252a34ff2e63eaeaea","likes":"30049","date":"8 years"},{"code":"f9ed69f08a5db83b5e6a2c70","likes":"29867","date":"8 years"},{"code":"f38181fce38aeaffd095e1d3","likes":"29584","date":"8 years"},{"code":"f4eeffdcd6f7a6b1e1424874","likes":"29230","date":"4 years"},{"code":"1b262c0f4c753282b8bbe1fa","likes":"27041","date":"4 years"},{"code":"a8d8eaaa96dafcbad3ffffd2","likes":"27010","date":"8 years"},{"code":"b7c4cfeee3cbd7c0ae967e76","likes":"26389","date":"1 year"},{"code":"ffb6b9fae3d9bbded661c0bf","likes":"26121","date":"6 years"},{"code":"b1b2ffaac4ffd2daffeef1ff","likes":"26028","date":"1 year"},{"code":"ffeddbedcdbbe3b7a0bf9270","likes":"24453","date":"2 years"},{"code":"6096b493bfcfbdcdd6eee9da","likes":"24438","date":"1 year"},{"code":"7d5a50b4846ce5b299fcdec0","likes":"24301","date":"2 years"},{"code":"364f6b3fc1c9f5f5f5fc5185","likes":"24235","date":"8 years"},{"code":"f9f5f6f8e8eefdcedff2bed1","likes":"24129","date":"10 months"},{"code":"defcf9cadefcc3bef0cca8e9","likes":"23787","date":"6 years"},{"code":"fcd1d1ece2e1d3e0dcaee1e1","likes":"23524","date":"3 years"},{"code":"8d7b68a4907cc8b6a6f1dec9","likes":"23518","date":"1 year"},{"code":"f8ede3bdd2b6a2b29f798777","likes":"23424","date":"2 years"},{"code":"f5efe6e8dfcaaebdca7895b2","likes":"22907","date":"1 year"},{"code":"fff8ea9e7676815b5b594545","likes":"22902","date":"1 year"},{"code":"f67280c06c846c5b7b355c7d","likes":"21779","date":"6 years"},{"code":"fefcf3f5ebe0f0dbdbdba39a","likes":"21256","date":"1 year"},{"code":"ffe6e6f2d1d1daeaf1c6dce4","likes":"21196","date":"1 year"},{"code":"fcd8d4fdf6f0f8e2cff5c6aa","likes":"21190","date":"2 years"},{"code":"27374d526d829db2bfdde6ed","likes":"21156","date":"10 months"},{"code":"2b2e4ae8454590374953354a","likes":"21136","date":"8 years"},{"code":"e4f9f530e3ca11999e40514e","likes":"21072","date":"8 years"},{"code":"2c36393f4e4fa27b5cdcd7c9","likes":"21025","date":"1 year"},{"code":"edf1d69dc08b60996640513b","likes":"20860","date":"1 year"},{"code":"2121213232320d737714ffec","likes":"20633","date":"7 years"},{"code":"f8ede3dfd3c3d0b8a87d6e83","likes":"20597","date":"1 year"},{"code":"f7fbfcd6e6f2b9d7ea769fcd","likes":"20550","date":"7 years"},{"code":"fdefeff4dfd0dad0c2cdbba7","likes":"20037","date":"2 years"},{"code":"93b5c6c9ccd5e4d8dcffe3e3","likes":"19723","date":"2 years"}]