[{"code":"cd5c08fff5e4c1d8c36a9c89","likes":"4218","date":"6 months"},{"code":"0d7c6641b3a2bde8cad7c3f1","likes":"2950","date":"6 months"},{"code":"c0c78ca6b37dfefae0b99470","likes":"7125","date":"6 months"},{"code":"2e073f7a1cacad49e1ebd3f8","likes":"6109","date":"6 months"},{"code":"ff8a8af4deb3f0eaaccce0ac","likes":"3510","date":"6 months"},{"code":"00712dd5ed9ffffbe6ff9100","likes":"3635","date":"6 months"},{"code":"1e201e3c3d37697565ecdfcc","likes":"6816","date":"6 months"},{"code":"3a10784e31aa3795bdf7f7f8","likes":"2531","date":"6 months"},{"code":"800000982b1cdad4b5f2e8c6","likes":"8934","date":"6 months"},{"code":"f7efe5e2bfd9c8a1e0674188","likes":"6843","date":"6 months"},{"code":"a28b5586ab89cbe2b5e7fbe6","likes":"2609","date":"6 months"},{"code":"d1e9f6f6eacbf1d3ceeecad5","likes":"9960","date":"7 months"},{"code":"f9dbba5b99c21a48701f316f","likes":"3765","date":"7 months"},{"code":"f8ede3dfd3c3d0b8a8c5705d","likes":"6228","date":"7 months"},{"code":"a02334ffad60ffeead96ceb4","likes":"4957","date":"7 months"},{"code":"ff8343f1dec6179bae4158a6","likes":"3571","date":"7 months"},{"code":"f6e96bbedc74a2ca71387f39","likes":"3160","date":"7 months"},{"code":"ccd5aee0e5b6faedcefefae0","likes":"6370","date":"7 months"},{"code":"b4d6cdffda76ff8c9eff4e88","likes":"5286","date":"7 months"},{"code":"921a40c75b7ad9ababf4d9d0","likes":"7854","date":"7 months"},{"code":"f0a8d0f7b5caffc6c6ffebd4","likes":"11108","date":"7 months"},{"code":"6482ad7fa1c3e2dad6f5eded","likes":"10160","date":"7 months"},{"code":"bc9f8bb5cfb7cadabfe7e8d8","likes":"3889","date":"7 months"},{"code":"7c00fef9e400ffaf00f5004f","likes":"3906","date":"7 months"},{"code":"5222588c3061c63c51d95f59","likes":"4383","date":"7 months"},{"code":"c9dabf9ca986808d7c5f6f65","likes":"6977","date":"7 months"},{"code":"1801614f1787eb3678fb773c","likes":"4693","date":"7 months"},{"code":"02152603346e6eacdae2e2b6","likes":"6621","date":"7 months"},{"code":"ffdfd6e3a5c7b692c2694f8e","likes":"6626","date":"7 months"},{"code":"f8ededff8225b43f3f173b45","likes":"4014","date":"7 months"},{"code":"914f1edeac80f7dcb9b5c18e","likes":"5017","date":"7 months"},{"code":"fef3e2bec6a0708871606676","likes":"4875","date":"7 months"},{"code":"201e43134b70508c9beeeeee","likes":"8621","date":"7 months"},{"code":"ef5a6ffff1dbd4bdac536493","likes":"4237","date":"7 months"},{"code":"f6fb7ab4e38088d66c73bba3","likes":"2784","date":"7 months"},{"code":"1a363640534c677d6ad6bd98","likes":"6764","date":"7 months"},{"code":"f8ede3dfd3c3d0b8a88d493a","likes":"6137","date":"7 months"},{"code":"399918ecffe6ffaaaaff7777","likes":"3106","date":"7 months"},{"code":"17153b2e236c433d8bc8acd6","likes":"6777","date":"7 months"},{"code":"f3feb8ffde4dffb22cff4c4c","likes":"3325","date":"7 months"}]