[{"code":"c3ff93ffdb5cffaf61ff70ab","likes":"2494","date":"2 months"},{"code":"fff9d0caf4ffa0deff5ab2ff","likes":"4823","date":"2 months"},{"code":"7469b6ad88c6e1afd1ffe6e6","likes":"6209","date":"2 months"},{"code":"cde8e5eef7ff7ab2b24d869c","likes":"7349","date":"2 months"},{"code":"03aed268d2e8fdde55feefad","likes":"3111","date":"2 months"},{"code":"f3ca52f6e9b20a68477aba78","likes":"3636","date":"2 months"},{"code":"fff2d7ffe0b5f8c794d8ae7e","likes":"4605","date":"2 months"},{"code":"32012f524c42e2dfd0f97300","likes":"1970","date":"2 months"},{"code":"640d6bb51b75e65c19f8d082","likes":"2282","date":"2 months"},{"code":"a87676ca8787e1acacffd0d0","likes":"7215","date":"2 months"},{"code":"fc4100ffc55a00215e2c4e80","likes":"3839","date":"2 months"},{"code":"c40c0cff6500ff8a08ffc100","likes":"4148","date":"3 months"},{"code":"ff76cefdffc294ffd8a3d8ff","likes":"3299","date":"3 months"},{"code":"f5dad2fcffe0bacd9275a47f","likes":"5477","date":"3 months"},{"code":"1a4d2e4f6f52e8dfcaf5efe6","likes":"6477","date":"3 months"},{"code":"121481ffeae3ffcbcbffb1b1","likes":"3358","date":"3 months"},{"code":"1534483c5b6f948979dfd0b8","likes":"7175","date":"3 months"},{"code":"fffbdaffec9effbb70ed9455","likes":"4114","date":"3 months"},{"code":"10439f874cccc65bcff27bbd","likes":"3599","date":"3 months"},{"code":"e4c59eaf8260803d3b322c2b","likes":"6113","date":"3 months"},{"code":"b5c18ef7dcb9deac80b99470","likes":"5100","date":"3 months"},{"code":"1e03420e46a39ac8cde1f7f5","likes":"4045","date":"3 months"},{"code":"fff5e08decb441b06e141e46","likes":"2668","date":"3 months"},{"code":"fefaf6eadbc8dac0a3102c57","likes":"4884","date":"3 months"},{"code":"f6f5f2f0ebe3f3d0d7ffefef","likes":"8550","date":"3 months"},{"code":"4793afffc470dd57468b322c","likes":"5041","date":"3 months"},{"code":"0741731679ab5debd7c5ff95","likes":"3106","date":"3 months"},{"code":"5bbcfffffab7ffd1e37ea1ff","likes":"3133","date":"3 months"},{"code":"1c16788576ff7bc9ffa3ffd6","likes":"3459","date":"3 months"},{"code":"dba979ecca9ce8efcfafd198","likes":"3732","date":"3 months"},{"code":"6c0345dc6b19f7c566fff8dc","likes":"2376","date":"3 months"},{"code":"003c43135d6677b0aae3fef7","likes":"6853","date":"3 months"},{"code":"a79277d1bb9eead8c0fff2e1","likes":"8057","date":"3 months"},{"code":"ffebb2e59be9d862bc8644a2","likes":"2374","date":"3 months"},{"code":"86469cbc7fcdfb9ad1ffcdea","likes":"4841","date":"3 months"},{"code":"a34343e9c874fbf8ddc0d6e8","likes":"3017","date":"3 months"},{"code":"b3c8cfbed7dcf1eedce5ddc5","likes":"9279","date":"3 months"},{"code":"49243e704264bb8493dbafa0","likes":"4026","date":"3 months"},{"code":"0c0c0c481e149b3922f2613f","likes":"4166","date":"3 months"},{"code":"ffc94ac08b5c795458453f78","likes":"2063","date":"3 months"}]