[{"code":"9195f6b7c9f2f9f07afb88b4","likes":"3611","date":"6 months"},{"code":"b5c0d0ccd3caf5e8ddeed3d9","likes":"12402","date":"6 months"},{"code":"fff67ebfea7c9bcf53416d19","likes":"4374","date":"6 months"},{"code":"2016581d24ca98abeef9e8c9","likes":"3905","date":"6 months"},{"code":"2650732d95969ad0c2f1fada","likes":"6413","date":"6 months"},{"code":"8e7ab5b784b7e493b3eea5a6","likes":"8895","date":"6 months"},{"code":"070f2b1b1a55535c919290c3","likes":"10092","date":"6 months"},{"code":"211951836fff15f5baf0f3ff","likes":"3845","date":"6 months"},{"code":"000000f72798f57d1febf400","likes":"3128","date":"6 months"},{"code":"d7e4c0c6dcbabbc3a4b3a398","likes":"5194","date":"6 months"},{"code":"8cb9bdfefbf6ecb159b67352","likes":"6216","date":"6 months"},{"code":"9b4444c68484a3c9aaeeeeee","likes":"2564","date":"6 months"},{"code":"7f27ff9f70fdfdbf60ff8911","likes":"2638","date":"6 months"},{"code":"211c6a59b4c374e291eff396","likes":"2477","date":"7 months"},{"code":"fff7f1ffe4c9e78895bed1cf","likes":"6854","date":"7 months"},{"code":"cdfadbf6fdc3ffcf96ff8080","likes":"4220","date":"7 months"},{"code":"944e63b47b84caa6a6ffe7e7","likes":"7524","date":"7 months"},{"code":"40a2e3fff6e9bbe2ec0d9276","likes":"4749","date":"7 months"},{"code":"b4b4b8c7c8cce3e1d9f2efe5","likes":"10152","date":"7 months"},{"code":"12372a436850adbc9ffbfada","likes":"11096","date":"7 months"},{"code":"e8c872fff3cfc9d7dd637a9f","likes":"4665","date":"7 months"},{"code":"1f2544474f7a81689dffd0ec","likes":"6738","date":"7 months"},{"code":"0c2d57fc6736ffb0b0efecec","likes":"4735","date":"7 months"},{"code":"eeedebe0ccbe7472643c3633","likes":"6511","date":"7 months"},{"code":"f28585ffa447fffc9bb7e5b4","likes":"3294","date":"7 months"},{"code":"fdf0d1ac7d8885586f643843","likes":"4986","date":"7 months"},{"code":"6c22a66962ad83c0c196e9c6","likes":"4295","date":"7 months"},{"code":"561c246d2932c7b7a3e8d8c4","likes":"7931","date":"7 months"},{"code":"d04848f3b95ffde7676895d2","likes":"4735","date":"7 months"},{"code":"0a1d56492e8737b5b6f2f597","likes":"2561","date":"7 months"},{"code":"e1f0dad4e7c5bfd8af99bc85","likes":"11328","date":"7 months"},{"code":"0000000b60b040a2d8f0edcf","likes":"4579","date":"7 months"},{"code":"294b2950623a789461dbe7c9","likes":"7621","date":"7 months"},{"code":"fe7a363652ad280274e9f6ff","likes":"3800","date":"7 months"},{"code":"dcffb7ff6868ffbb64ffeaa7","likes":"3410","date":"7 months"},{"code":"f5eee6fff8e3f3d7cae6a4b4","likes":"14321","date":"7 months"},{"code":"0306373c0753720455910a67","likes":"8234","date":"7 months"},{"code":"f9efdbebd9b49dbc98638889","likes":"8645","date":"7 months"},{"code":"a94438d24545e6baa3e4debe","likes":"4444","date":"7 months"},{"code":"3e3232503c3c7e6363a87c7c","likes":"6764","date":"7 months"}]